<Properties StartupConfiguration="{3263827B-544A-D989-4741-7829AFAFB382}|">
  <MonoDevelop.Ide.Workbench ActiveDocument="Assets/Scripts/Shroom.cs">
    <Files>
      <File FileName="Assets/Scripts/GameManager.cs" Line="120" Column="1" />
      <File FileName="Assets/Scripts/SleepingBag.cs" />
      <File FileName="Assets/Scripts/WorldTime.cs" Line="35" Column="18" />
      <File FileName="Assets/Scripts/NewMonoBehaviour.cs" Line="17" Column="46" />
      <File FileName="Assets/Scripts/UIInteractable.cs" Line="25" Column="5" />
      <File FileName="Assets/Scripts/InventorySystem.cs" Line="54" Column="22" />
      <File FileName="Assets/Scripts/Shroom.cs" Line="33" Column="10" />
    </Files>
    <Pads>
      <Pad Id="ProjectPad">
        <State name="__root__">
          <Node name="Mayor NPC" expanded="True">
            <Node name="Assets" expanded="True">
              <Node name="Scripts" expanded="True">
                <Node name="Shroom.cs" selected="True" />
              </Node>
            </Node>
          </Node>
        </State>
      </Pad>
    </Pads>
  </MonoDevelop.Ide.Workbench>
  <MonoDevelop.Ide.DebuggingService.PinnedWatches />
  <MonoDevelop.Ide.Workspace ActiveConfiguration="Debug" />
  <MonoDevelop.Ide.ItemProperties.Assembly-CSharp PreferredExecutionTarget="d9b082bc-00bf-4515-98f5-28a890284c52" />
  <MonoDevelop.Ide.DebuggingService.Breakpoints>
    <BreakpointStore>
      <Breakpoint enabled="false" file="/Users/charleshache/Desktop/Revised-Mayor-NPC/Mayor NPC/Assets/Scripts/PlayerController.cs" relfile="Assets/Scripts/PlayerController.cs" line="44" column="1" />
      <Breakpoint enabled="false" file="/Users/charleshache/Desktop/Revised-Mayor-NPC/Mayor NPC/Assets/Scripts/PlayerController.cs" relfile="Assets/Scripts/PlayerController.cs" line="39" column="1" />
      <Breakpoint enabled="false" file="/Users/charleshache/Desktop/Revised-Mayor-NPC/Mayor NPC/Assets/Scripts/PlayerController.cs" relfile="Assets/Scripts/PlayerController.cs" line="113" column="1" />
      <Breakpoint enabled="false" file="/Users/charleshache/Desktop/Revised-Mayor-NPC/Mayor NPC/Assets/Scripts/PlayerController.cs" relfile="Assets/Scripts/PlayerController.cs" line="111" column="1" />
      <Breakpoint enabled="false" file="/Users/charleshache/Desktop/Revised-Mayor-NPC/Mayor NPC/Assets/Scripts/PlayerController.cs" relfile="Assets/Scripts/PlayerController.cs" line="108" column="1" />
      <Breakpoint enabled="false" file="/Users/charleshache/Desktop/Revised-Mayor-NPC/Mayor NPC/Assets/Scripts/PlayerController.cs" relfile="Assets/Scripts/PlayerController.cs" line="124" column="1" />
      <Breakpoint enabled="false" file="/Users/charleshache/Desktop/Revised-Mayor-NPC/Mayor NPC/Assets/Scripts/PlayerController.cs" relfile="Assets/Scripts/PlayerController.cs" line="126" column="1" />
      <Breakpoint file="/Users/charleshache/Desktop/Revised-Mayor-NPC/Mayor NPC/Assets/Scripts/EnemySpawner.cs" relfile="Assets/Scripts/EnemySpawner.cs" line="98" column="1" />
      <Breakpoint file="/Users/charleshache/Desktop/Revised-Mayor-NPC/Mayor NPC/Assets/Scripts/MouseUI.cs" relfile="Assets/Scripts/MouseUI.cs" line="83" column="1" />
    </BreakpointStore>
  </MonoDevelop.Ide.DebuggingService.Breakpoints>
  <MultiItemStartupConfigurations />
</Properties>